LICENSE.txt
MANIFEST.in
README.rst
VERSION.txt
pycompssenv
pyproject.toml
setup.py
url
src/pycompss/__init__.py
src/pycompss.egg-info/PKG-INFO
src/pycompss.egg-info/SOURCES.txt
src/pycompss.egg-info/dependency_links.txt
src/pycompss.egg-info/requires.txt
src/pycompss.egg-info/top_level.txt