Metadata-Version: 2.4
Name: pycompss
Version: 3.3.3
Summary: Python Binding for COMP Superscalar Runtime
Author-email: "The COMPSs team - Workflows and Distributed Computing Group (WDC) - Barcelona Supercomputing Center (BSC)" <support-compss@bsc.es>
Maintainer-email: "The COMPSs team - Workflows and Distributed Computing Group (WDC) - Barcelona Supercomputing Center (BSC)" <support-compss@bsc.es>
License: 
Project-URL: Homepage, http://compss.bsc.es
Project-URL: Documentation, https://pycompss.readthedocs.io/
Project-URL: Repository, https://github.com/bsc-wdc/compss
Project-URL: Issues, https://github.com/bsc-wdc/compss/issues
Project-URL: Changelog, https://github.com/bsc-wdc/compss/blob/stable/changelog
Keywords: distributed computing,PyCOMPSs,COMPSs,HPC,parallelization
Classifier: Development Status :: 5 - Production/Stable
Classifier: Environment :: Console
Classifier: Intended Audience :: Science/Research
Classifier: Intended Audience :: Developers
Classifier: Intended Audience :: Information Technology
Classifier: License :: OSI Approved :: Apache Software License
Classifier: Operating System :: Unix
Classifier: Operating System :: POSIX :: Linux
Classifier: Operating System :: MacOS
Classifier: Programming Language :: C
Classifier: Programming Language :: C++
Classifier: Programming Language :: Java
Classifier: Programming Language :: Python :: 3
Classifier: Programming Language :: Python :: 3.7
Classifier: Programming Language :: Python :: 3.8
Classifier: Programming Language :: Python :: 3.9
Classifier: Programming Language :: Python :: 3.10
Classifier: Programming Language :: Python :: 3.11
Classifier: Programming Language :: Python :: 3.12
Classifier: Programming Language :: Python :: 3 :: Only
Classifier: Topic :: System :: Distributed Computing
Classifier: Topic :: Scientific/Engineering
Classifier: Topic :: Software Development
Classifier: Topic :: Utilities
Requires-Python: >=3.7
License-File: LICENSE.txt
Provides-Extra: extended
Requires-Dist: dill; extra == "extended"
Requires-Dist: numpy; extra == "extended"
Requires-Dist: jupyter; extra == "extended"
Dynamic: license-file
